Lkinpy/Simulator_ABCD.py
Lkinpy/Simulator_ABCD_linearOnly.py
Lkinpy/Simulator_ABCDv1.py
Lkinpy/Simulator_Hybrid.py
Lkinpy/Simulator_P0.py
Lkinpy/__init__.py
Lkinpy/base.py
Lkinpy/core.py
Lkinpy-0.0.0.dist-info/LICENSE
Lkinpy-0.0.0.dist-info/METADATA
Lkinpy-0.0.0.dist-info/WHEEL
Lkinpy-0.0.0.dist-info/top_level.txt
Lkinpy-0.0.0.dist-info/RECORD
