Metadata-Version: 2.1
Name: Lkinpy
Version: 0.0.0
Summary: Package for simulating simple kinetic inductance mixers.
Author-email: Grant Giesbrecht <grant.giesbrecht@colorado.edu>
Project-URL: Homepage, https://github.com/Grant-Giesbrecht/Lkpy
Project-URL: Bug Tracker, https://github.com/Grant-Giesbrecht/Lkpy/issues
Classifier: Programming Language :: Python :: 3
Classifier: License :: OSI Approved :: MIT License
Classifier: Operating System :: OS Independent
Requires-Python: >=3.7
License-File: LICENSE
